README.rst
pyproject.toml
setup.py
./skquant/__init__.py
./skquant/_version.py
./skquant/interop/__init__.py
./skquant/interop/qiskit.py
./skquant/interop/scipy.py
./skquant/opt/__init__.py
./skquant/opt/_norbitR.py
./skquant/opt/_pybobyqa.py
scikit_quant.egg-info/PKG-INFO
scikit_quant.egg-info/SOURCES.txt
scikit_quant.egg-info/dependency_links.txt
scikit_quant.egg-info/requires.txt
scikit_quant.egg-info/top_level.txt
test/test_optimizers.py
test/test_regression.py