Metadata-Version: 2.1
Name: scikit-quant
Version: 0.8.2
Summary: Integrator for Python-based quantum computing software
Home-page: http://scikit-quant.org
Maintainer: Wim Lavrijsen
Maintainer-email: WLavrijsen@lbl.gov
License: LBNL BSD
Keywords: quantum computing optimizers
Platform: UNKNOWN
Classifier: Development Status :: 2 - Pre-Alpha
Classifier: Intended Audience :: Science/Research
Classifier: Intended Audience :: Developers
Classifier: Intended Audience :: Developers
Classifier: Intended Audience :: Science/Research
Classifier: Topic :: Scientific/Engineering
Classifier: Topic :: Scientific/Engineering :: Chemistry
Classifier: Topic :: Scientific/Engineering :: Mathematics
Classifier: Topic :: Scientific/Engineering :: Physics
Classifier: Topic :: Software Development
Classifier: License :: OSI Approved :: BSD License
Classifier: Programming Language :: Python :: 2
Classifier: Programming Language :: Python :: 2.7
Classifier: Programming Language :: Python :: 3
Classifier: Programming Language :: Python :: 3.6
Classifier: Programming Language :: Python :: 3.7
Classifier: Programming Language :: C++
Classifier: Natural Language :: English
Provides-Extra: NOMAD
